synthe/__init__.py
synthe/adaptivehistsampler.py
synthe/bayesiantweediesalesgenerator.py
synthe/conformal_inference.py
synthe/diffusion.py
synthe/distro_simulator.py
synthe/diversity_generator.py
synthe/empirical_copula.py
synthe/healthsims.py
synthe/helpers.py
synthe/meboot.py
synthe/metrics.py
synthe/row_subsampling.py
synthe/stratified_sampling.py
synthe/synthetictabular.py
synthe/ts_distro_simulator.py
synthe/utils.py
synthe-0.10.0.dist-info/licenses/LICENSE
synthe-0.10.0.dist-info/METADATA
synthe-0.10.0.dist-info/WHEEL
synthe-0.10.0.dist-info/entry_points.txt
synthe-0.10.0.dist-info/top_level.txt
synthe-0.10.0.dist-info/RECORD
