Metadata-Version: 2.4
Name: synthe
Version: 0.10.0
Summary: synthetic simulation
Author-email: "T. Moudiki" <thierry.moudiki@gmail.com>
Maintainer-email: "T. Moudiki" <thierry.moudiki@gmail.com>
License: The Clear BSD License
Project-URL: bugs, https://github.com/Techtonique/synthe/issues
Project-URL: changelog, https://github.com/Techtonique/synthe/blob/master/changelog.md
Project-URL: homepage, https://github.com/Techtonique/synthe
Classifier: Development Status :: 4 - Beta
Classifier: Intended Audience :: Science/Research
Classifier: Intended Audience :: Developers
Classifier: License :: OSI Approved :: BSD License
Classifier: Operating System :: MacOS
Classifier: Operating System :: Microsoft :: Windows
Classifier: Operating System :: POSIX
Classifier: Programming Language :: Python :: 3.10
Classifier: Programming Language :: Python :: 3.11
Classifier: Programming Language :: Python :: 3.12
Classifier: Topic :: Software Development
Classifier: Topic :: Scientific/Engineering
Requires-Python: >=3.10
License-File: LICENSE
Requires-Dist: numpy
Requires-Dist: matplotlib
Requires-Dist: nnetsauce
Requires-Dist: GPopt
Requires-Dist: tqdm
Requires-Dist: properscoring
Requires-Dist: optuna
Requires-Dist: wordcloud
Requires-Dist: seaborn
Provides-Extra: dev
Requires-Dist: black[jupyter]; extra == "dev"
Requires-Dist: build; extra == "dev"
Requires-Dist: Cython>=3.0.10; extra == "dev"
Requires-Dist: pytest; extra == "dev"
Requires-Dist: ruff; extra == "dev"
Requires-Dist: setuptools-scm>=8; extra == "dev"
Requires-Dist: black[jupyter]; extra == "dev"
Requires-Dist: build; extra == "dev"
Requires-Dist: Cython>=3.0.10; extra == "dev"
Requires-Dist: pytest; extra == "dev"
Requires-Dist: ruff; extra == "dev"
Requires-Dist: setuptools-scm>=8; extra == "dev"
Requires-Dist: sphinx; extra == "dev"
Requires-Dist: furo; extra == "dev"
Dynamic: license-file
